treescriptify_text/__init__.py
treescriptify_text/__main__.py
treescriptify_text/argument_parser.py
treescriptify_text/file_validation.py
treescriptify_text/input_data.py
treescriptify_text/script_writer.py
treescriptify_text/string_validation.py
treescriptify_text/tree_node_data.py
treescriptify_text/tree_reader.py
treescriptify_text-0.3.1.dist-info/LICENSE
treescriptify_text-0.3.1.dist-info/METADATA
treescriptify_text-0.3.1.dist-info/WHEEL
treescriptify_text-0.3.1.dist-info/entry_points.txt
treescriptify_text-0.3.1.dist-info/top_level.txt
treescriptify_text-0.3.1.dist-info/RECORD
