Metadata-Version: 2.1
Name: treescriptify-text
Version: 0.3.1
Summary: Create TreeScript from a Text file that contains tree-like file information.
Home-page: https://github.com/DK96-OS/treescriptify-text
Author: DK96-OS
License: GPLv3
Project-URL: Issues, https://github.com/DK96-OS/treescriptify-text/issues
Project-URL: Source Code, https://github.com/DK96-OS/treescriptify-text
Keywords: treescript
Classifier: Natural Language :: English
Classifier: Operating System :: OS Independent
Classifier: Intended Audience :: Developers
Classifier: License :: OSI Approved :: GNU General Public License v3 (GPLv3)
Classifier: Programming Language :: Python :: 3
Classifier: Programming Language :: Python :: 3.10
Classifier: Programming Language :: Python :: 3.11
Classifier: Programming Language :: Python :: 3.12
Classifier: Programming Language :: Python :: 3.13
Requires-Python: >=3.10
License-File: LICENSE
